pytratto/__init__.py
pytratto/connectivity/Connectivity.py
pytratto/connectivity/__init__.py
pytratto/examples/__init__.py
pytratto/examples/test.py
pytratto/systems/Systems.py
pytratto/systems/__init__.py
py_tratto-0.0.3.dist-info/LICENSE
py_tratto-0.0.3.dist-info/METADATA
py_tratto-0.0.3.dist-info/WHEEL
py_tratto-0.0.3.dist-info/top_level.txt
py_tratto-0.0.3.dist-info/RECORD
